aek_lregr_trainer/__init__.py
aek_lregr_trainer/models/__init__.py
aek_lregr_trainer/models/ann.py
aek_lregr_trainer/trainers/__init__.py
aek_lregr_trainer/trainers/classification_trainer.py
aek_lregr_trainer/trainers/regression_trainer.py
aek_lregr_trainer/utils/__init__.py
aek_lregr_trainer/utils/metrics.py
aek_lregr_trainer/utils/preprocessing.py
aek_lregr_trainer-0.4.1.dist-info/licenses/LICENSE
aek_lregr_trainer-0.4.1.dist-info/METADATA
aek_lregr_trainer-0.4.1.dist-info/WHEEL
aek_lregr_trainer-0.4.1.dist-info/top_level.txt
aek_lregr_trainer-0.4.1.dist-info/RECORD
